setup.py
glamkit_holdingpage.egg-info/PKG-INFO
glamkit_holdingpage.egg-info/SOURCES.txt
glamkit_holdingpage.egg-info/dependency_links.txt
glamkit_holdingpage.egg-info/not-zip-safe
glamkit_holdingpage.egg-info/top_level.txt
holdingpage/__init__.py
holdingpage/decorators.py
holdingpage/hooks.py
holdingpage/middleware.py
holdingpage/models.py
holdingpage/tests/__init__.py
holdingpage/tests/urls.py
holdingpage/tests/testapp/__init__.py
holdingpage/tests/testapp/models.py
holdingpage/tests/testapp/views.py